[
    {
        "ActivityId":  "F67ABD7E-DE59-499D-9D21-2E6D37443266",
        "AdditionalParams":  {

                             },
        "Flags":  1024,
        "Health":  {
                       "LastErrorCode":  0,
                       "LastUpdateTime":  132457839158393219
                   },
        "ID":  "35397CD7-695D-485A-8356-9BE3172040D4",
        "IsApplied":  false,
        "Policies":  [
                         {
                             "ExternalPort":  8080,
                             "InternalPort":  80,
                             "Protocol":  6,
                             "SourceVIP":  "10.0.0.2",
                             "Type":  "ELB"
                         }
                     ],
        "References":  [
                           "00000000-0000-0000-0000-100000000000"
                       ],
        "Resources":  {
                          "AdditionalParams":  {

                                               },
                          "AllocationOrder":  1,
                          "Allocators":  [
                                             {
                                                 "AdditionalParams":  {

                                                                      },
                                                 "AllocationOrder":  0,
                                                 "DestinationVIPMappingRef":  0,
                                                 "ExternalPort":  8080,
                                                 "Health":  {
                                                                "LastErrorCode":  0,
                                                                "LastUpdateTime":  132457839158473119
                                                            },
                                                 "ID":  "BEF0CA19-7E34-446B-99BE-5866F59E905D",
                                                 "ILB":  false,
                                                 "InternalPort":  80,
                                                 "IsDSR":  false,
                                                 "IsPolicy":  true,
                                                 "LocalRoutedVip":  false,
                                                 "NatPool":  "SLB_NATPOOL_IPV4_TCP_0",
                                                 "Protocol":  6,
                                                 "SourceVIPMappingRe":  1,
                                                 "SourceVip":  "10.0.0.2",
                                                 "State":  3,
                                                 "TCPPortAllocate":  true,
                                                 "Tag":  "VFP ELB Policy Non Dsr",
                                                 "UDPPortAllocate":  false
                                             }
                                         ],
                          "Health":  {
                                         "LastErrorCode":  0,
                                         "LastUpdateTime":  132457839158393219
                                     },
                          "ID":  "F67ABD7E-DE59-499D-9D21-2E6D37443266",
                          "PortOperationTime":  0,
                          "State":  1,
                          "SwitchOperationTime":  0,
                          "VfpOperationTime":  0
                      },
        "State":  2,
        "Version":  38654705667
    },
    {
        "ActivityId":  "5C6CC309-38C7-4E21-A54F-B5E62A002D67",
        "AdditionalParams":  {

                             },
        "Flags":  1024,
        "Health":  {
                       "LastErrorCode":  0,
                       "LastUpdateTime":  132457839158195362
                   },
        "ID":  "AB0861D9-2DD2-45DE-9623-BF1C919A3241",
        "IsApplied":  false,
        "Policies":  [
                         {
                             "ExternalPort":  0,
                             "ILB":  true,
                             "InternalPort":  0,
                             "SourceVIP":  "10.0.0.2",
                             "Type":  "ELB",
                             "VIPs":  [
                                          "10.0.0.3"
                                      ]
                         }
                     ],
        "References":  [
                           "00000000-0000-0000-0000-100000000000"
                       ],
        "Resources":  {
                          "AdditionalParams":  {

                                               },
                          "AllocationOrder":  1,
                          "Allocators":  [
                                             {
                                                 "AdditionalParams":  {

                                                                      },
                                                 "AllocationOrder":  0,
                                                 "DestinationVIPMappingRef":  2,
                                                 "ExternalPort":  0,
                                                 "Health":  {
                                                                "LastErrorCode":  0,
                                                                "LastUpdateTime":  132457839158195362
                                                            },
                                                 "ID":  "54E863C6-3E54-48FF-BFA1-56AACD17BA25",
                                                 "ILB":  true,
                                                 "InternalPort":  0,
                                                 "IsDSR":  false,
                                                 "IsPolicy":  true,
                                                 "LocalRoutedVip":  false,
                                                 "NatPool":  "SLB_NATPOOL_IPV4_UDP_0",
                                                 "Protocol":  0,
                                                 "SourceVIPMappingRe":  2,
                                                 "SourceVip":  "10.0.0.2",
                                                 "State":  3,
                                                 "TCPPortAllocate":  true,
                                                 "Tag":  "VFP ELB Policy Non Dsr",
                                                 "UDPPortAllocate":  true,
                                                 "VIP_0":  "10.0.0.3"
                                             }
                                         ],
                          "Health":  {
                                         "LastErrorCode":  0,
                                         "LastUpdateTime":  132457839158195362
                                     },
                          "ID":  "5C6CC309-38C7-4E21-A54F-B5E62A002D67",
                          "PortOperationTime":  0,
                          "State":  1,
                          "SwitchOperationTime":  0,
                          "VfpOperationTime":  0
                      },
        "State":  2,
        "Version":  38654705667
    },
    {
        "ActivityId":  "C9F7AA1B-AE95-467C-97B3-F8BC4155D85A",
        "AdditionalParams":  {

                             },
        "Flags":  1024,
        "Health":  {
                       "LastErrorCode":  0,
                       "LastUpdateTime":  132457839159611022
                   },
        "ID":  "3DD6D8E2-78FE-4DC7-9721-4E33C46FAD2D",
        "IsApplied":  false,
        "Policies":  [
                         {
                             "ExternalPort":  0,
                             "ILB":  true,
                             "InternalPort":  0,
                             "SourceVIP":  "10.0.1.4",
                             "Type":  "ELB",
                             "VIPs":  [
                                          "10.0.1.2"
                                      ]
                         }
                     ],
        "References":  [
                           "00000000-0000-0000-0000-300000000000"
                       ],
        "Resources":  {
                          "AdditionalParams":  {

                                               },
                          "AllocationOrder":  1,
                          "Allocators":  [
                                             {
                                                 "AdditionalParams":  {

                                                                      },
                                                 "AllocationOrder":  0,
                                                 "DestinationVIPMappingRef":  2,
                                                 "ExternalPort":  0,
                                                 "Health":  {
                                                                "LastErrorCode":  0,
                                                                "LastUpdateTime":  132457839159680877
                                                            },
                                                 "ID":  "653272FF-DD25-46F0-B5EE-2119B78E8E42",
                                                 "ILB":  true,
                                                 "InternalPort":  0,
                                                 "IsDSR":  false,
                                                 "IsPolicy":  true,
                                                 "LocalRoutedVip":  false,
                                                 "NatPool":  "SLB_NATPOOL_IPV4_UDP_0",
                                                 "Protocol":  0,
                                                 "SourceVIPMappingRe":  2,
                                                 "SourceVip":  "10.0.1.4",
                                                 "State":  3,
                                                 "TCPPortAllocate":  true,
                                                 "Tag":  "VFP ELB Policy Non Dsr",
                                                 "UDPPortAllocate":  true,
                                                 "VIP_0":  "10.0.1.2"
                                             }
                                         ],
                          "Health":  {
                                         "LastErrorCode":  0,
                                         "LastUpdateTime":  132457839159611022
                                     },
                          "ID":  "C9F7AA1B-AE95-467C-97B3-F8BC4155D85A",
                          "PortOperationTime":  0,
                          "State":  1,
                          "SwitchOperationTime":  0,
                          "VfpOperationTime":  0
                      },
        "State":  2,
        "Version":  38654705667
    }
]
